{"nodes": [{"id": "repo_archive_kod_margo_scripts_design_lint_sh", "label": "design-lint.sh", "file_type": "code", "source_file": "scripts/design-lint.sh", "source_location": "L1", "metadata": {"language": "bash", "kind": "file"}}, {"id": "repo_archive_kod_margo_scripts_design_lint_sh__entry", "label": "design-lint.sh script", "file_type": "code", "source_file": "scripts/design-lint.sh", "source_location": "L1", "metadata": {"language": "bash", "kind": "bash_entrypoint"}}, {"id": "repo_archive_kod_margo_scripts_design_lint_strip_comments", "label": "strip_comments()", "file_type": "code", "source_file": "scripts/design-lint.sh", "source_location": "L24", "metadata": {"language": "bash", "kind": "bash_function"}}, {"id": "repo_archive_kod_margo_scripts_design_lint_report", "label": "report()", "file_type": "code", "source_file": "scripts/design-lint.sh", "source_location": "L28", "metadata": {"language": "bash", "kind": "bash_function"}}], "edges": [{"source": "repo_archive_kod_margo_scripts_design_lint_sh", "target": "repo_archive_kod_margo_scripts_design_lint_sh__entry", "relation": "contains", "confidence": "EXTRACTED", "source_file": "scripts/design-lint.sh", "source_location": "L1", "weight": 1.0}, {"source": "repo_archive_kod_margo_scripts_design_lint_sh", "target": "repo_archive_kod_margo_scripts_design_lint_strip_comments", "relation": "defines", "confidence": "EXTRACTED", "source_file": "scripts/design-lint.sh", "source_location": "L24", "weight": 1.0}, {"source": "repo_archive_kod_margo_scripts_design_lint_sh", "target": "repo_archive_kod_margo_scripts_design_lint_report", "relation": "defines", "confidence": "EXTRACTED", "source_file": "scripts/design-lint.sh", "source_location": "L28", "weight": 1.0}, {"source": "repo_archive_kod_margo_scripts_design_lint_sh__entry", "target": "repo_archive_kod_margo_scripts_design_lint_report", "relation": "calls", "confidence": "EXTRACTED", "source_file": "scripts/design-lint.sh", "source_location": "L42", "weight": 1.0, "context": "call"}]}